main.py
macos_clipboard_mcp-1.0.2.dist-info/METADATA
macos_clipboard_mcp-1.0.2.dist-info/WHEEL
macos_clipboard_mcp-1.0.2.dist-info/entry_points.txt
macos_clipboard_mcp-1.0.2.dist-info/top_level.txt
macos_clipboard_mcp-1.0.2.dist-info/RECORD
