Metadata-Version: 2.4
Name: macos-clipboard-mcp
Version: 1.0.2
Summary: A simple utility that provides model context protocol (MCP) tools for interacting with the macOS clipboard.
Requires-Python: >=3.12
Requires-Dist: applescript
Requires-Dist: build>=1.2.2.post1
Requires-Dist: mcp[cli]>=1.7.1
Requires-Dist: pillow>=11.2.1
